cli/__init__.py
cli/commands/__init__.py
cli/commands/auth/__init__.py
cli/commands/auth/login.py
cli/commands/config_promotion/__init__.py
cli/commands/config_promotion/config_promotion.py
cli/commands/context.py
cli/commands/empower_api/__init__.py
cli/commands/empower_api/data_model_config.py
cli/commands/empower_api/environment_databricks.py
cli/commands/empower_api/file_object_match.py
cli/commands/empower_api/processing_step_command.py
cli/commands/empower_api/source.py
cli/commands/empower_api/source_list.py
cli/commands/empower_api/source_object_list.py
cli/commands/empower_discovery/__init__.py
cli/commands/empower_discovery/auth_url.py
cli/commands/empower_discovery/endpoint_mapping.py
cli/commands/empower_discovery/enterprise.py
cli/commands/source_types/__init__.py
cli/commands/source_types/execution_contexts.py
cli/commands/source_types/source_types.py
cli/commands/source_types/source_types_service_urls.py
cli/commands/user_service/__init__.py
cli/commands/user_service/principals.py
cli/commands/user_service/roles.py
cli/common/__init__.py
cli/common/auth/__init__.py
cli/common/auth/auth.py
cli/common/auth/config.py
cli/common/auth/manager.py
cli/common/auth/openid_client.py
cli/common/auth/parse_token.py
cli/common/auth/pipeline_auth.py
cli/common/auth/server.py
cli/common/auth/templates/error.html
cli/common/auth/templates/success.html
cli/common/command_help.py
cli/common/command_util.py
cli/common/crud_command_base.py
cli/common/enums.py
cli/common/file_utils.py
cli/common/schemas.py
cli/common/service_type.py
cli/common/store_client.py
cli/common/util.py
cli/common/validation.py
cli/main.py
empower_cli-2.0.0.dist-info/entry_points.txt
empower_cli-2.0.0.dist-info/METADATA
empower_cli-2.0.0.dist-info/LICENSE
empower_cli-2.0.0.dist-info/WHEEL
empower_cli-2.0.0.dist-info/RECORD
