Metadata-Version: 2.1
Name: empower-cli
Version: 2.0.0
Summary: Empower cli client for API interaction
Home-page: https://github.com/hitachisolutionsamerica/empower/tree/development/tools/empower_cli
License: MIT
Author: Empower Team
Author-email: empower@hitachisolutions.com
Requires-Python: >=3.9,<4.0
Classifier: License :: OSI Approved :: MIT License
Classifier: Programming Language :: Python :: 3
Classifier: Programming Language :: Python :: 3.9
Classifier: Programming Language :: Python :: 3.10
Classifier: Programming Language :: Python :: 3.11
Requires-Dist: PyJWT (>=2.6.0,<3.0.0)
Requires-Dist: PyYAML (>=6.0,<7.0)
Requires-Dist: cryptography (>=38.0.3,<39.0.0)
Requires-Dist: pickleDB (>=0.9.2,<0.10.0)
Requires-Dist: pydantic (>=1.9.1,<2.0.0)
Requires-Dist: python-dotenv (>=0.20.0,<0.21.0)
Requires-Dist: python-keycloak (>=2.0.0,<3.0.0)
Requires-Dist: requests (>=2.28.1,<3.0.0)
Requires-Dist: typer (>=0.5.0,<0.6.0)
Project-URL: Repository, https://github.com/hitachisolutionsamerica/empower/tree/development/tools/empower_cli
